kumo_api-0.57.1.dist-info/licenses/LICENSE
kumoapi/__init__.py
kumoapi/common.py
kumoapi/data_snapshot.py
kumoapi/data_source.py
kumoapi/distilled_model_plan.py
kumoapi/encoder.py
kumoapi/graph.py
kumoapi/jobs.py
kumoapi/json_serde.py
kumoapi/model_plan.py
kumoapi/online_serving.py
kumoapi/source_table.py
kumoapi/table.py
kumoapi/task.py
kumoapi/train.py
kumoapi/typing.py
kumoapi/explain/__init__.py
kumoapi/explain/column_analysis.py
kumoapi/explain/common.py
kumoapi/explain/gradient.py
kumoapi/explain/rfm.py
kumoapi/explain/subgraph.py
kumoapi/pquery/__init__.py
kumoapi/pquery/utils.py
kumoapi/pquery/validated_predictive_query.py
kumoapi/pquery/AST/__init__.py
kumoapi/pquery/AST/aggregation.py
kumoapi/pquery/AST/ast_node.py
kumoapi/pquery/AST/column.py
kumoapi/pquery/AST/condition.py
kumoapi/pquery/AST/constant.py
kumoapi/pquery/AST/date_offset_range.py
kumoapi/pquery/AST/filter.py
kumoapi/pquery/AST/join.py
kumoapi/pquery/AST/location_interval.py
kumoapi/pquery/AST/logical_operation.py
kumoapi/rfm/__init__.py
kumoapi/rfm/context.py
kumoapi/rfm/explain.py
kumoapi/rfm/pquery.py
kumoapi/rfm/requests.py
kumoapi/rfm/protos/.gitignore
kumoapi/rfm/protos/__init__.py
kumoapi/rfm/protos/context.proto
kumoapi/rfm/protos/context_pb2.py
kumoapi/rfm/protos/request.proto
kumoapi/rfm/protos/request_pb2.py
kumo_api-0.57.1.dist-info/METADATA
kumo_api-0.57.1.dist-info/WHEEL
kumo_api-0.57.1.dist-info/top_level.txt
kumo_api-0.57.1.dist-info/RECORD
