Metadata-Version: 2.4
Name: kumo-api
Version: 0.57.1
Summary: RESTful datamodels for Kumo AI
Author-email: "Kumo.AI" <hello@kumo.ai>
License-Expression: MIT
Project-URL: homepage, https://kumo.ai
Project-URL: documentation, https://kumo.ai/docs
Keywords: deep-learning,graph-neural-networks,cloud-data-warehouse
Classifier: Development Status :: 5 - Production/Stable
Classifier: Programming Language :: Python
Classifier: Programming Language :: Python :: 3.10
Classifier: Programming Language :: Python :: 3.11
Classifier: Programming Language :: Python :: 3.12
Classifier: Programming Language :: Python :: 3.13
Classifier: Programming Language :: Python :: 3 :: Only
Requires-Python: >=3.10
License-File: LICENSE
Requires-Dist: pydantic!=2.0.*,!=2.1.*,!=2.2.*,!=2.3.*,!=2.4.*,!=2.5.*,!=2.6.*
Requires-Dist: protobuf>=3.19.0
Requires-Dist: numpy
Requires-Dist: pandas
Provides-Extra: test
Requires-Dist: pytest; extra == "test"
Requires-Dist: pyarrow; extra == "test"
Requires-Dist: tabulate; extra == "test"
Provides-Extra: release-check
Requires-Dist: boto3; extra == "release-check"
Dynamic: license-file
